stickybisht/__init__.py
stickybisht/__main__.py
stickybisht/stickybisht_notes.py
stickybisht-0.1.1.dist-info/METADATA
stickybisht-0.1.1.dist-info/WHEEL
stickybisht-0.1.1.dist-info/entry_points.txt
stickybisht-0.1.1.dist-info/licenses/LICENSE
stickybisht-0.1.1.dist-info/RECORD
